presentation/bubble_fsm2.v
module bubble_sort_FSM(clk,reset,in_data,out_data,n);
input clk;
input reset;
input [31:0]in_data;
output reg [31:0]out_data;
input [31:0]n;
reg sorted=0;
integer i,j,k,p,q;
reg in_valid=0;
reg stage1=0;
reg stage2=0;
reg stage3=0;
reg created=0;
reg [31:0]array[100000:0];
reg [31:0]array2[100000:0];
reg [100000:0]input_index=0;
reg [100000:0]input_index2=0;
reg [100000:0]outer_loop=0;
reg [100000:0]output_index=0;
always @(posedge clk)
begin
  if(reset==0)
  begin
   input_index<='d0;
   input_index2<='d0;
   output_index<='d0;
   outer_loop<='d0;
   sorted<=0;
   stage1<=0;
   stage2<=0;
   stage3<=0;
   for(i=0;i<n;i=i+1)
   begin
     array[i]<='d0;
     array2[i]<='d0;
   end
  end
  if(reset==1 && stage1==0)
  begin
    input_index<=input_index+1'b1;
    if(input_index<n)
    begin
      array[input_index]<=in_data;
    end
    else
    begin
       stage1<=1;
    end
  end
  if(reset==1 && stage1==1 && stage2==0)
  begin
    for(i=0;i<n;i=i+1)
    begin
      array2[i]<=array[i];
    end
      stage1<=0;
      stage2<=1;
      input_index2<=input_index;
      input_index<=0;
  end
  if(reset==1 && stage2==1 && sorted==0)
  begin
    if(outer_loop<input_index2-1)
      outer_loop<=outer_loop+1;
    else
      sorted<=1;
  end
  if(reset==1 && stage2==1 && sorted==0)
  begin
     if(outer_loop[0:0]==1)
     begin
      for(j=1;j<n-1;j=j+2)
      begin
       if(array2[j]<array2[j+1])
       begin
        array2[j]<=array2[j+1];
        array2[j+1]<=array2[j];
       end
     end
    end
    else
    begin
       for(k=0;k<n-1;k=k+2)
        begin
         if(array2[k]<array2[k+1])
         begin
          array2[k]<=array2[k+1];
          array2[k+1]<=array2[k];
         end
        end
    end
  end

  if(reset==1 && sorted==1)
  begin
    output_index<=output_index+1'b1;
      if(output_index<n)
      begin
       out_data<=array2[output_index];
      end
      else
      begin
       sorted<=0;
       stage2<=0;
       outer_loop<=0;
       output_index<=0;
      end
  end
end
endmodule

presentation/bubble_fsm_tb.v
`include "bubble_fsm2.v"
module bubble_sort_tb();
reg clk;
reg reset=1;
reg [31:0]in_data;
reg [31:0]n;
wire [31:0]out_data;
bubble_sort_FSM DUT(.clk(clk),.reset(reset),.in_data(in_data),.out_data(out_data),.n(n));
/*initial begin
reset=0;
repeat(1)
#1 reset=~(reset);
end*/
initial begin
clk=1;
repeat(1000)
#5 clk=~(clk);
end
initial begin
/*n=10; in_data=9999; #10;
in_data=2; #10;
in_data=2350; #10;
in_data=3598; #10;
in_data=5346; #10;
in_data=7891; #10;
in_data=3456; #10;
in_data=1234; #10;
in_data=2345; #10;
in_data=4576; #25;

n=10; in_data=11; #10;
in_data=12; #10;
in_data=13; #10;
in_data=14; #10;
in_data=15; #10;
in_data=1; #10;
in_data=2; #10;
in_data=3; #10;
in_data=4; #10;
in_data=5; #10;*/

n=5; in_data=11; #10;
in_data=12; #10;
in_data=13; #10;
in_data=14; #10;
in_data=15; #10;

end
initial begin
$dumpfile("bubble_sort_tb.vcd");
$dumpvars(0,bubble_sort_tb);
end
endmodule

presentation/bubble_sort_tb.vcd
$date
	Sun Dec  2 11:26:55 2018
$end
$version
	Icarus Verilog
$end
$timescale
	1s
$end
$scope module bubble_sort_tb $end
$var wire 32 ! out_data [31:0] $end
$var reg 1 " clk $end
$var reg 32 # in_data [31:0] $end
$var reg 32 $ n [31:0] $end
$var reg 1 % reset $end
$scope module DUT $end
$var wire 1 " clk $end
$var wire 32 & in_data [31:0] $end
$var wire 32 ' n [31:0] $end
$var wire 1 % reset $end
$var reg 1 ( created $end
$var reg 1 ) in_valid $end
$var reg 100001 * input_index [100000:0] $end
$var reg 100001 + input_index2 [100000:0] $end
$var reg 32 , out_data [31:0] $end
$var reg 100001 - outer_loop [100000:0] $end
$var reg 100001 . output_index [100000:0] $end
$var reg 1 / sorted $end
$var reg 1 0 stage1 $end
$var reg 1 1 stage2 $end
$var reg 1 2 stage3 $end
$var integer 32 3 i [31:0] $end
$var integer 32 4 j [31:0] $end
$var integer 32 5 k [31:0] $end
$upscope $end
$upscope $end
$enddefinitions $end
#0
$dumpvars
bx 5
bx 4
bx 3
02
01
00
0/
b0 .
b0 -
bx ,
b0 +
b1 *
0)
0(
b101 '
b1011 &
1%
b101 $
b1011 #
1"
bx !
$end
#5
0"
#10
b10 *
1"
b1100 #
b1100 &
#15
0"
#20
b11 *
1"
b1101 #
b1101 &
#25
0"
#30
b100 *
1"
b1110 #
b1110 &
#35
0"
#40
b101 *
1"
b1111 #
b1111 &
#45
0"
#50
10
b110 *
1"
#55
0"
#60
b0 *
b110 +
11
00
b101 3
1"
#65
0"
#70
b1 -
b1 *
b100 5
1"
#75
0"
#80
b10 -
b10 *
b101 4
1"
#85
0"
#90
b11 -
b11 *
b100 5
1"
#95
0"
#100
b100 -
b100 *
b101 4
1"
#105
0"
#110
b101 -
b101 *
b100 5
1"
#115
0"
#120
1/
10
b110 *
b101 4
1"
#125
0"
#130
b1111 !
b1111 ,
b1 .
1"
#135
0"
#140
b1110 !
b1110 ,
b10 .
1"
#145
0"
#150
b1101 !
b1101 ,
b11 .
1"
#155
0"
#160
b1100 !
b1100 ,
b100 .
1"
#165
0"
#170
b1011 !
b1011 ,
b101 .
1"
#175
0"
#180
b0 -
01
0/
b0 .
1"
#185
0"
#190
b0 *
11
00
b101 3
1"
#195
0"
#200
b1 -
b1 *
b100 5
1"
#205
0"
#210
b10 -
b10 *
b101 4
1"
#215
0"
#220
b11 -
b11 *
b100 5
1"
#225
0"
#230
b100 -
b100 *
b101 4
1"
#235
0"
#240
b101 -
b101 *
b100 5
1"
#245
0"
#250
1/
10
b110 *
b101 4
1"
#255
0"
#260
b1111 !
b1111 ,
b1 .
1"
#265
0"
#270
b10 .
1"
#275
0"
#280
b11 .
1"
#285
0"
#290
b100 .
1"
#295
0"
#300
b101 .
1"
#305
0"
#310
b0 -
01
0/
b0 .
1"
#315
0"
#320
b0 *
11
00
b101 3
1"
#325
0"
#330
b1 -
b1 *
b100 5
1"
#335
0"
#340
b10 -
b10 *
b101 4
1"
#345
0"
#350
b11 -
b11 *
b100 5
1"
#355
0"
#360
b100 -
b100 *
b101 4
1"
#365
0"
#370
b101 -
b101 *
b100 5
1"
#375
0"
#380
1/
10
b110 *
b101 4
1"
#385
0"
#390
b1 .
1"
#395
0"
#400
b10 .
1"
#405
0"
#410
b11 .
1"
#415
0"
#420
b100 .
1"
#425
0"
#430
b101 .
1"
#435
0"
#440
b0 -
01
0/
b0 .
1"
#445
0"
#450
b0 *
11
00
b101 3
1"
#455
0"
#460
b1 -
b1 *
b100 5
1"
#465
0"
#470
b10 -
b10 *
b101 4
1"
#475
0"
#480
b11 -
b11 *
b100 5
1"
#485
0"
#490
b100 -
b100 *
b101 4
1"
#495
0"
#500
b101 -
b101 *
b100 5
1"
#505
0"
#510
1/
10
b110 *
b101 4
1"
#515
0"
#520
b1 .
1"
#525
0"
#530
b10 .
1"
#535
0"
#540
b11 .
1"
#545
0"
#550
b100 .
1"
#555
0"
#560
b101 .
1"
#565
0"
#570
b0 -
01
0/
b0 .
1"
#575
0"
#580
b0 *
11
00
b101 3
1"
#585
0"
#590
b1 -
b1 *
b100 5
1"
#595
0"
#600
b10 -
b10 *
b101 4
1"
#605
0"
#610
b11 -
b11 *
b100 5
1"
#615
0"
#620
b100 -
b100 *
b101 4
1"
#625
0"
#630
b101 -
b101 *
b100 5
1"
#635
0"
#640
1/
10
b110 *
b101 4
1"
#645
0"
#650
b1 .
1"
#655
0"
#660
b10 .
1"
#665
0"
#670
b11 .
1"
#675
0"
#680
b100 .
1"
#685
0"
#690
b101 .
1"
#695
0"
#700
b0 -
01
0/
b0 .
1"
#705
0"
#710
b0 *
11
00
b101 3
1"
#715
0"
#720
b1 -
b1 *
b100 5
1"
#725
0"
#730
b10 -
b10 *
b101 4
1"
#735
0"
#740
b11 -
b11 *
b100 5
1"
#745
0"
#750
b100 -
b100 *
b101 4
1"
#755
0"
#760
b101 -
b101 *
b100 5
1"
#765
0"
#770
1/
10
b110 *
b101 4
1"
#775
0"
#780
b1 .
1"
#785
0"
#790
b10 .
1"
#795
0"
#800
b11 .
1"
#805
0"
#810
b100 .
1"
#815
0"
#820
b101 .
1"
#825
0"
#830
b0 -
01
0/
b0 .
1"
#835
0"
#840
b0 *
11
00
b101 3
1"
#845
0"
#850
b1 -
b1 *
b100 5
1"
#855
0"
#860
b10 -
b10 *
b101 4
1"
#865
0"
#870
b11 -
b11 *
b100 5
1"
#875
0"
#880
b100 -
b100 *
b101 4
1"
#885
0"
#890
b101 -
b101 *
b100 5
1"
#895
0"
#900
1/
10
b110 *
b101 4
1"
#905
0"
#910
b1 .
1"
#915
0"
#920
b10 .
1"
#925
0"
#930
b11 .
1"
#935
0"
#940
b100 .
1"
#945
0"
#950
b101 .
1"
#955
0"
#960
b0 -
01
0/
b0 .
1"
#965
0"
#970
b0 *
11
00
b101 3
1"
#975
0"
#980
b1 -
b1 *
b100 5
1"
#985
0"
#990
b10 -
b10 *
b101 4
1"
#995
0"
#1000
b11 -
b11 *
b100 5
1"
#1005
0"
#1010
b100 -
b100 *
b101 4
1"
#1015
0"
#1020
b101 -
b101 *
b100 5
1"
#1025
0"
#1030
1/
10
b110 *
b101 4
1"
#1035
0"
#1040
b1 .
1"
#1045
0"
#1050
b10 .
1"
#1055
0"
#1060
b11 .
1"
#1065
0"
#1070
b100 .
1"
#1075
0"
#1080
b101 .
1"
#1085
0"
#1090
b0 -
01
0/
b0 .
1"
#1095
0"
#1100
b0 *
11
00
b101 3
1"
#1105
0"
#1110
b1 -
b1 *
b100 5
1"
#1115
0"
#1120
b10 -
b10 *
b101 4
1"
#1125
0"
#1130
b11 -
b11 *
b100 5
1"
#1135
0"
#1140
b100 -
b100 *
b101 4
1"
#1145
0"
#1150
b101 -
b101 *
b100 5
1"
#1155
0"
#1160
1/
10
b110 *
b101 4
1"
#1165
0"
#1170
b1 .
1"
#1175
0"
#1180
b10 .
1"
#1185
0"
#1190
b11 .
1"
#1195
0"
#1200
b100 .
1"
#1205
0"
#1210
b101 .
1"
#1215
0"
#1220
b0 -
01
0/
b0 .
1"
#1225
0"
#1230
b0 *
11
00
b101 3
1"
#1235
0"
#1240
b1 -
b1 *
b100 5
1"
#1245
0"
#1250
b10 -
b10 *
b101 4
1"
#1255
0"
#1260
b11 -
b11 *
b100 5
1"
#1265
0"
#1270
b100 -
b100 *
b101 4
1"
#1275
0"
#1280
b101 -
b101 *
b100 5
1"
#1285
0"
#1290
1/
10
b110 *
b101 4
1"
#1295
0"
#1300
b1 .
1"
#1305
0"
#1310
b10 .
1"
#1315
0"
#1320
b11 .
1"
#1325
0"
#1330
b100 .
1"
#1335
0"
#1340
b101 .
1"
#1345
0"
#1350
b0 -
01
0/
b0 .
1"
#1355
0"
#1360
b0 *
11
00
b101 3
1"
#1365
0"
#1370
b1 -
b1 *
b100 5
1"
#1375
0"
#1380
b10 -
b10 *
b101 4
1"
#1385
0"
#1390
b11 -
b11 *
b100 5
1"
#1395
0"
#1400
b100 -
b100 *
b101 4
1"
#1405
0"
#1410
b101 -
b101 *
b100 5
1"
#1415
0"
#1420
1/
10
b110 *
b101 4
1"
#1425
0"
#1430
b1 .
1"
#1435
0"
#1440
b10 .
1"
#1445
0"
#1450
b11 .
1"
#1455
0"
#1460
b100 .
1"
#1465
0"
#1470
b101 .
1"
#1475
0"
#1480
b0 -
01
0/
b0 .
1"
#1485
0"
#1490
b0 *
11
00
b101 3
1"
#1495
0"
#1500
b1 -
b1 *
b100 5
1"
#1505
0"
#1510
b10 -
b10 *
b101 4
1"
#1515
0"
#1520
b11 -
b11 *
b100 5
1"
#1525
0"
#1530
b100 -
b100 *
b101 4
1"
#1535
0"
#1540
b101 -
b101 *
b100 5
1"
#1545
0"
#1550
1/
10
b110 *
b101 4
1"
#1555
0"
#1560
b1 .
1"
#1565
0"
#1570
b10 .
1"
#1575
0"
#1580
b11 .
1"
#1585
0"
#1590
b100 .
1"
#1595
0"
#1600
b101 .
1"
#1605
0"
#1610
b0 -
01
0/
b0 .
1"
#1615
0"
#1620
b0 *
11
00
b101 3
1"
#1625
0"
#1630
b1 -
b1 *
b100 5
1"
#1635
0"
#1640
b10 -
b10 *
b101 4
1"
#1645
0"
#1650
b11 -
b11 *
b100 5
1"
#1655
0"
#1660
b100 -
b100 *
b101 4
1"
#1665
0"
#1670
b101 -
b101 *
b100 5
1"
#1675
0"
#1680
1/
10
b110 *
b101 4
1"
#1685
0"
#1690
b1 .
1"
#1695
0"
#1700
b10 .
1"
#1705
0"
#1710
b11 .
1"
#1715
0"
#1720
b100 .
1"
#1725
0"
#1730
b101 .
1"
#1735
0"
#1740
b0 -
01
0/
b0 .
1"
#1745
0"
#1750
b0 *
11
00
b101 3
1"
#1755
0"
#1760
b1 -
b1 *
b100 5
1"
#1765
0"
#1770
b10 -
b10 *
b101 4
1"
#1775
0"
#1780
b11 -
b11 *
b100 5
1"
#1785
0"
#1790
b100 -
b100 *
b101 4
1"
#1795
0"
#1800
b101 -
b101 *
b100 5
1"
#1805
0"
#1810
1/
10
b110 *
b101 4
1"
#1815
0"
#1820
b1 .
1"
#1825
0"
#1830
b10 .
1"
#1835
0"
#1840
b11 .
1"
#1845
0"
#1850
b100 .
1"
#1855
0"
#1860
b101 .
1"
#1865
0"
#1870
b0 -
01
0/
b0 .
1"
#1875
0"
#1880
b0 *
11
00
b101 3
1"
#1885
0"
#1890
b1 -
b1 *
b100 5
1"
#1895
0"
#1900
b10 -
b10 *
b101 4
1"
#1905
0"
#1910
b11 -
b11 *
b100 5
1"
#1915
0"
#1920
b100 -
b100 *
b101 4
1"
#1925
0"
#1930
b101 -
b101 *
b100 5
1"
#1935
0"
#1940
1/
10
b110 *
b101 4
1"
#1945
0"
#1950
b1 .
1"
#1955
0"
#1960
b10 .
1"
#1965
0"
#1970
b11 .
1"
#1975
0"
#1980
b100 .
1"
#1985
0"
#1990
b101 .
1"
#1995
0"
#2000
b0 -
01
0/
b0 .
1"
#2005
0"
#2010
b0 *
11
00
b101 3
1"
#2015
0"
#2020
b1 -
b1 *
b100 5
1"
#2025
0"
#2030
b10 -
b10 *
b101 4
1"
#2035
0"
#2040
b11 -
b11 *
b100 5
1"
#2045
0"
#2050
b100 -
b100 *
b101 4
1"
#2055
0"
#2060
b101 -
b101 *
b100 5
1"
#2065
0"
#2070
1/
10
b110 *
b101 4
1"
#2075
0"
#2080
b1 .
1"
#2085
0"
#2090
b10 .
1"
#2095
0"
#2100
b11 .
1"
#2105
0"
#2110
b100 .
1"
#2115
0"
#2120
b101 .
1"
#2125
0"
#2130
b0 -
01
0/
b0 .
1"
#2135
0"
#2140
b0 *
11
00
b101 3
1"
#2145
0"
#2150
b1 -
b1 *
b100 5
1"
#2155
0"
#2160
b10 -
b10 *
b101 4
1"
#2165
0"
#2170
b11 -
b11 *
b100 5
1"
#2175
0"
#2180
b100 -
b100 *
b101 4
1"
#2185
0"
#2190
b101 -
b101 *
b100 5
1"
#2195
0"
#2200
1/
10
b110 *
b101 4
1"
#2205
0"
#2210
b1 .
1"
#2215
0"
#2220
b10 .
1"
#2225
0"
#2230
b11 .
1"
#2235
0"
#2240
b100 .
1"
#2245
0"
#2250
b101 .
1"
#2255
0"
#2260
b0 -
01
0/
b0 .
1"
#2265
0"
#2270
b0 *
11
00
b101 3
1"
#2275
0"
#2280
b1 -
b1 *
b100 5
1"
#2285
0"
#2290
b10 -
b10 *
b101 4
1"
#2295
0"
#2300
b11 -
b11 *
b100 5
1"
#2305
0"
#2310
b100 -
b100 *
b101 4
1"
#2315
0"
#2320
b101 -
b101 *
b100 5
1"
#2325
0"
#2330
1/
10
b110 *
b101 4
1"
#2335
0"
#2340
b1 .
1"
#2345
0"
#2350
b10 .
1"
#2355
0"
#2360
b11 .
1"
#2365
0"
#2370
b100 .
1"
#2375
0"
#2380
b101 .
1"
#2385
0"
#2390
b0 -
01
0/
b0 .
1"
#2395
0"
#2400
b0 *
11
00
b101 3
1"
#2405
0"
#2410
b1 -
b1 *
b100 5
1"
#2415
0"
#2420
b10 -
b10 *
b101 4
1"
#2425
0"
#2430
b11 -
b11 *
b100 5
1"
#2435
0"
#2440
b100 -
b100 *
b101 4
1"
#2445
0"
#2450
b101 -
b101 *
b100 5
1"
#2455
0"
#2460
1/
10
b110 *
b101 4
1"
#2465
0"
#2470
b1 .
1"
#2475
0"
#2480
b10 .
1"
#2485
0"
#2490
b11 .
1"
#2495
0"
#2500
b100 .
1"
#2505
0"
#2510
b101 .
1"
#2515
0"
#2520
b0 -
01
0/
b0 .
1"
#2525
0"
#2530
b0 *
11
00
b101 3
1"
#2535
0"
#2540
b1 -
b1 *
b100 5
1"
#2545
0"
#2550
b10 -
b10 *
b101 4
1"
#2555
0"
#2560
b11 -
b11 *
b100 5
1"
#2565
0"
#2570
b100 -
b100 *
b101 4
1"
#2575
0"
#2580
b101 -
b101 *
b100 5
1"
#2585
0"
#2590
1/
10
b110 *
b101 4
1"
#2595
0"
#2600
b1 .
1"
#2605
0"
#2610
b10 .
1"
#2615
0"
#2620
b11 .
1"
#2625
0"
#2630
b100 .
1"
#2635
0"
#2640
b101 .
1"
#2645
0"
#2650
b0 -
01
0/
b0 .
1"
#2655
0"
#2660
b0 *
11
00
b101 3
1"
#2665
0"
#2670
b1 -
b1 *
b100 5
1"
#2675
0"
#2680
b10 -
b10 *
b101 4
1"
#2685
0"
#2690
b11 -
b11 *
b100 5
1"
#2695
0"
#2700
b100 -
b100 *
b101 4
1"
#2705
0"
#2710
b101 -
b101 *
b100 5
1"
#2715
0"
#2720
1/
10
b110 *
b101 4
1"
#2725
0"
#2730
b1 .
1"
#2735
0"
#2740
b10 .
1"
#2745
0"
#2750
b11 .
1"
#2755
0"
#2760
b100 .
1"
#2765
0"
#2770
b101 .
1"
#2775
0"
#2780
b0 -
01
0/
b0 .
1"
#2785
0"
#2790
b0 *
11
00
b101 3
1"
#2795
0"
#2800
b1 -
b1 *
b100 5
1"
#2805
0"
#2810
b10 -
b10 *
b101 4
1"
#2815
0"
#2820
b11 -
b11 *
b100 5
1"
#2825
0"
#2830
b100 -
b100 *
b101 4
1"
#2835
0"
#2840
b101 -
b101 *
b100 5
1"
#2845
0"
#2850
1/
10
b110 *
b101 4
1"
#2855
0"
#2860
b1 .
1"
#2865
0"
#2870
b10 .
1"
#2875
0"
#2880
b11 .
1"
#2885
0"
#2890
b100 .
1"
#2895
0"
#2900
b101 .
1"
#2905
0"
#2910
b0 -
01
0/
b0 .
1"
#2915
0"
#2920
b0 *
11
00
b101 3
1"
#2925
0"
#2930
b1 -
b1 *
b100 5
1"
#2935
0"
#2940
b10 -
b10 *
b101 4
1"
#2945
0"
#2950
b11 -
b11 *
b100 5
1"
#2955
0"
#2960
b100 -
b100 *
b101 4
1"
#2965
0"
#2970
b101 -
b101 *
b100 5
1"
#2975
0"
#2980
1/
10
b110 *
b101 4
1"
#2985
0"
#2990
b1 .
1"
#2995
0"
#3000
b10 .
1"
#3005
0"
#3010
b11 .
1"
#3015
0"
#3020
b100 .
1"
#3025
0"
#3030
b101 .
1"
#3035
0"
#3040
b0 -
01
0/
b0 .
1"
#3045
0"
#3050
b0 *
11
00
b101 3
1"
#3055
0"
#3060
b1 -
b1 *
b100 5
1"
#3065
0"
#3070
b10 -
b10 *
b101 4
1"
#3075
0"
#3080
b11 -
b11 *
b100 5
1"
#3085
0"
#3090
b100 -
b100 *
b101 4
1"
#3095
0"
#3100
b101 -
b101 *
b100 5
1"
#3105
0"
#3110
1/
10
b110 *
b101 4
1"
#3115
0"
#3120
b1 .
1"
#3125
0"
#3130
b10 .
1"
#3135
0"
#3140
b11 .
1"
#3145
0"
#3150
b100 .
1"
#3155
0"
#3160
b101 .
1"
#3165
0"
#3170
b0 -
01
0/
b0 .
1"
#3175
0"
#3180
b0 *
11
00
b101 3
1"
#3185
0"
#3190
b1 -
b1 *
b100 5
1"
#3195
0"
#3200
b10 -
b10 *
b101 4
1"
#3205
0"
#3210
b11 -
b11 *
b100 5
1"
#3215
0"
#3220
b100 -
b100 *
b101 4
1"
#3225
0"
#3230
b101 -
b101 *
b100 5
1"
#3235
0"
#3240
1/
10
b110 *
b101 4
1"
#3245
0"
#3250
b1 .
1"
#3255
0"
#3260
b10 .
1"
#3265
0"
#3270
b11 .
1"
#3275
0"
#3280
b100 .
1"
#3285
0"
#3290
b101 .
1"
#3295
0"
#3300
b0 -
01
0/
b0 .
1"
#3305
0"
#3310
b0 *
11
00
b101 3
1"
#3315
0"
#3320
b1 -
b1 *
b100 5
1"
#3325
0"
#3330
b10 -
b10 *
b101 4
1"
#3335
0"
#3340
b11 -
b11 *
b100 5
1"
#3345
0"
#3350
b100 -
b100 *
b101 4
1"
#3355
0"
#3360
b101 -
b101 *
b100 5
1"
#3365
0"
#3370
1/
10
b110 *
b101 4
1"
#3375
0"
#3380
b1 .
1"
#3385
0"
#3390
b10 .
1"
#3395
0"
#3400
b11 .
1"
#3405
0"
#3410
b100 .
1"
#3415
0"
#3420
b101 .
1"
#3425
0"
#3430
b0 -
01
0/
b0 .
1"
#3435
0"
#3440
b0 *
11
00
b101 3
1"
#3445
0"
#3450
b1 -
b1 *
b100 5
1"
#3455
0"
#3460
b10 -
b10 *
b101 4
1"
#3465
0"
#3470
b11 -
b11 *
b100 5
1"
#3475
0"
#3480
b100 -
b100 *
b101 4
1"
#3485
0"
#3490
b101 -
b101 *
b100 5
1"
#3495
0"
#3500
1/
10
b110 *
b101 4
1"
#3505
0"
#3510
b1 .
1"
#3515
0"
#3520
b10 .
1"
#3525
0"
#3530
b11 .
1"
#3535
0"
#3540
b100 .
1"
#3545
0"
#3550
b101 .
1"
#3555
0"
#3560
b0 -
01
0/
b0 .
1"
#3565
0"
#3570
b0 *
11
00
b101 3
1"
#3575
0"
#3580
b1 -
b1 *
b100 5
1"
#3585
0"
#3590
b10 -
b10 *
b101 4
1"
#3595
0"
#3600
b11 -
b11 *
b100 5
1"
#3605
0"
#3610
b100 -
b100 *
b101 4
1"
#3615
0"
#3620
b101 -
b101 *
b100 5
1"
#3625
0"
#3630
1/
10
b110 *
b101 4
1"
#3635
0"
#3640
b1 .
1"
#3645
0"
#3650
b10 .
1"
#3655
0"
#3660
b11 .
1"
#3665
0"
#3670
b100 .
1"
#3675
0"
#3680
b101 .
1"
#3685
0"
#3690
b0 -
01
0/
b0 .
1"
#3695
0"
#3700
b0 *
11
00
b101 3
1"
#3705
0"
#3710
b1 -
b1 *
b100 5
1"
#3715
0"
#3720
b10 -
b10 *
b101 4
1"
#3725
0"
#3730
b11 -
b11 *
b100 5
1"
#3735
0"
#3740
b100 -
b100 *
b101 4
1"
#3745
0"
#3750
b101 -
b101 *
b100 5
1"
#3755
0"
#3760
1/
10
b110 *
b101 4
1"
#3765
0"
#3770
b1 .
1"
#3775
0"
#3780
b10 .
1"
#3785
0"
#3790
b11 .
1"
#3795
0"
#3800
b100 .
1"
#3805
0"
#3810
b101 .
1"
#3815
0"
#3820
b0 -
01
0/
b0 .
1"
#3825
0"
#3830
b0 *
11
00
b101 3
1"
#3835
0"
#3840
b1 -
b1 *
b100 5
1"
#3845
0"
#3850
b10 -
b10 *
b101 4
1"
#3855
0"
#3860
b11 -
b11 *
b100 5
1"
#3865
0"
#3870
b100 -
b100 *
b101 4
1"
#3875
0"
#3880
b101 -
b101 *
b100 5
1"
#3885
0"
#3890
1/
10
b110 *
b101 4
1"
#3895
0"
#3900
b1 .
1"
#3905
0"
#3910
b10 .
1"
#3915
0"
#3920
b11 .
1"
#3925
0"
#3930
b100 .
1"
#3935
0"
#3940
b101 .
1"
#3945
0"
#3950
b0 -
01
0/
b0 .
1"
#3955
0"
#3960
b0 *
11
00
b101 3
1"
#3965
0"
#3970
b1 -
b1 *
b100 5
1"
#3975
0"
#3980
b10 -
b10 *
b101 4
1"
#3985
0"
#3990
b11 -
b11 *
b100 5
1"
#3995
0"
#4000
b100 -
b100 *
b101 4
1"
#4005
0"
#4010
b101 -
b101 *
b100 5
1"
#4015
0"
#4020
1/
10
b110 *
b101 4
1"
#4025
0"
#4030
b1 .
1"
#4035
0"
#4040
b10 .
1"
#4045
0"
#4050
b11 .
1"
#4055
0"
#4060
b100 .
1"
#4065
0"
#4070
b101 .
1"
#4075
0"
#4080
b0 -
01
0/
b0 .
1"
#4085
0"
#4090
b0 *
11
00
b101 3
1"
#4095
0"
#4100
b1 -
b1 *
b100 5
1"
#4105
0"
#4110
b10 -
b10 *
b101 4
1"
#4115
0"
#4120
b11 -
b11 *
b100 5
1"
#4125
0"
#4130
b100 -
b100 *
b101 4
1"
#4135
0"
#4140
b101 -
b101 *
b100 5
1"
#4145
0"
#4150
1/
10
b110 *
b101 4
1"
#4155
0"
#4160
b1 .
1"
#4165
0"
#4170
b10 .
1"
#4175
0"
#4180
b11 .
1"
#4185
0"
#4190
b100 .
1"
#4195
0"
#4200
b101 .
1"
#4205
0"
#4210
b0 -
01
0/
b0 .
1"
#4215
0"
#4220
b0 *
11
00
b101 3
1"
#4225
0"
#4230
b1 -
b1 *
b100 5
1"
#4235
0"
#4240
b10 -
b10 *
b101 4
1"
#4245
0"
#4250
b11 -
b11 *
b100 5
1"
#4255
0"
#4260
b100 -
b100 *
b101 4
1"
#4265
0"
#4270
b101 -
b101 *
b100 5
1"
#4275
0"
#4280
1/
10
b110 *
b101 4
1"
#4285
0"
#4290
b1 .
1"
#4295
0"
#4300
b10 .
1"
#4305
0"
#4310
b11 .
1"
#4315
0"
#4320
b100 .
1"
#4325
0"
#4330
b101 .
1"
#4335
0"
#4340
b0 -
01
0/
b0 .
1"
#4345
0"
#4350
b0 *
11
00
b101 3
1"
#4355
0"
#4360
b1 -
b1 *
b100 5
1"
#4365
0"
#4370
b10 -
b10 *
b101 4
1"
#4375
0"
#4380
b11 -
b11 *
b100 5
1"
#4385
0"
#4390
b100 -
b100 *
b101 4
1"
#4395
0"
#4400
b101 -
b101 *
b100 5
1"
#4405
0"
#4410
1/
10
b110 *
b101 4
1"
#4415
0"
#4420
b1 .
1"
#4425
0"
#4430
b10 .
1"
#4435
0"
#4440
b11 .
1"
#4445
0"
#4450
b100 .
1"
#4455
0"
#4460
b101 .
1"
#4465
0"
#4470
b0 -
01
0/
b0 .
1"
#4475
0"
#4480
b0 *
11
00
b101 3
1"
#4485
0"
#4490
b1 -
b1 *
b100 5
1"
#4495
0"
#4500
b10 -
b10 *
b101 4
1"
#4505
0"
#4510
b11 -
b11 *
b100 5
1"
#4515
0"
#4520
b100 -
b100 *
b101 4
1"
#4525
0"
#4530
b101 -
b101 *
b100 5
1"
#4535
0"
#4540
1/
10
b110 *
b101 4
1"
#4545
0"
#4550
b1 .
1"
#4555
0"
#4560
b10 .
1"
#4565
0"
#4570
b11 .
1"
#4575
0"
#4580
b100 .
1"
#4585
0"
#4590
b101 .
1"
#4595
0"
#4600
b0 -
01
0/
b0 .
1"
#4605
0"
#4610
b0 *
11
00
b101 3
1"
#4615
0"
#4620
b1 -
b1 *
b100 5
1"
#4625
0"
#4630
b10 -
b10 *
b101 4
1"
#4635
0"
#4640
b11 -
b11 *
b100 5
1"
#4645
0"
#4650
b100 -
b100 *
b101 4
1"
#4655
0"
#4660
b101 -
b101 *
b100 5
1"
#4665
0"
#4670
1/
10
b110 *
b101 4
1"
#4675
0"
#4680
b1 .
1"
#4685
0"
#4690
b10 .
1"
#4695
0"
#4700
b11 .
1"
#4705
0"
#4710
b100 .
1"
#4715
0"
#4720
b101 .
1"
#4725
0"
#4730
b0 -
01
0/
b0 .
1"
#4735
0"
#4740
b0 *
11
00
b101 3
1"
#4745
0"
#4750
b1 -
b1 *
b100 5
1"
#4755
0"
#4760
b10 -
b10 *
b101 4
1"
#4765
0"
#4770
b11 -
b11 *
b100 5
1"
#4775
0"
#4780
b100 -
b100 *
b101 4
1"
#4785
0"
#4790
b101 -
b101 *
b100 5
1"
#4795
0"
#4800
1/
10
b110 *
b101 4
1"
#4805
0"
#4810
b1 .
1"
#4815
0"
#4820
b10 .
1"
#4825
0"
#4830
b11 .
1"
#4835
0"
#4840
b100 .
1"
#4845
0"
#4850
b101 .
1"
#4855
0"
#4860
b0 -
01
0/
b0 .
1"
#4865
0"
#4870
b0 *
11
00
b101 3
1"
#4875
0"
#4880
b1 -
b1 *
b100 5
1"
#4885
0"
#4890
b10 -
b10 *
b101 4
1"
#4895
0"
#4900
b11 -
b11 *
b100 5
1"
#4905
0"
#4910
b100 -
b100 *
b101 4
1"
#4915
0"
#4920
b101 -
b101 *
b100 5
1"
#4925
0"
#4930
1/
10
b110 *
b101 4
1"
#4935
0"
#4940
b1 .
1"
#4945
0"
#4950
b10 .
1"
#4955
0"
#4960
b11 .
1"
#4965
0"
#4970
b100 .
1"
#4975
0"
#4980
b101 .
1"
#4985
0"
#4990
b0 -
01
0/
b0 .
1"
#4995
0"
#5000
b0 *
11
00
b101 3
1"
