lab1/halfadder.v
module halfadder(in1,in2,sum,carry);
	input in1,in2;
	output sum,carry;
	assign sum = in1 ^ in2;
	assign carry = in1 & in2;
endmodule

lab1/fulladder.v
`include "halfadder.v"
module fulladder(a,b,c_in,sum,c_out);
	input a,b,c_in;
	output sum,c_out;
	halfadder h1(a,b,sum1,c_1);
	halfadder h2(sum1,c_in,sum,c_2);
	assign c_out = c_1 | c_2; 
endmodule

lab1/testbfa.v
`include "fulladder.v"
module testing;
	reg a,b,c;
	wire sum,carry;
	fulladder f(a,b,c,sum,carry);
	initial begin
		a <= 0;
		b <= 0;
		c <= 0;
	#5
		a <= 0;
		b <= 0;
		c <= 1;
	#5
		a <= 0;
		b <= 1;
		c <= 0;
	#5
		a <= 0;
		b <= 1;
		c <= 1;
	#5	
		a <= 1;
		b <= 0;
		c <= 0;
	#5	
		a <= 1;
		b <= 0;
		c <= 1;
	#5
		a <= 1;
		b <= 1;
		c <= 0;
	#5	
		a <= 1;
		b <= 1;
		c <= 1;
	#5	
		$display(sum,carry);
	end

	initial begin
		$dumpfile("testf.vcd");
		$dumpvars(0,testing);	
	end
endmodule

lab1/testf.vcd
$date
	Thu Aug  9 00:52:21 2018
$end
$version
	Icarus Verilog
$end
$timescale
	1s
$end
$scope module testing $end
$var wire 1 ! sum $end
$var wire 1 " carry $end
$var reg 1 # a $end
$var reg 1 $ b $end
$var reg 1 % c $end
$scope module f $end
$var wire 1 # a $end
$var wire 1 $ b $end
$var wire 1 % c_in $end
$var wire 1 " c_out $end
$var wire 1 & sum1 $end
$var wire 1 ! sum $end
$var wire 1 ' c_2 $end
$var wire 1 ( c_1 $end
$scope module h1 $end
$var wire 1 ( carry $end
$var wire 1 # in1 $end
$var wire 1 $ in2 $end
$var wire 1 & sum $end
$upscope $end
$scope module h2 $end
$var wire 1 ' carry $end
$var wire 1 & in1 $end
$var wire 1 % in2 $end
$var wire 1 ! sum $end
$upscope $end
$upscope $end
$upscope $end
$enddefinitions $end
#0
$dumpvars
0(
0'
0&
0%
0$
0#
0"
0!
$end
#5
1!
1%
#10
1&
0%
1$
#15
1"
0!
1'
1%
#20
0"
1!
0'
0%
0$
1#
#25
1"
0!
1'
1%
#30
0'
0&
1(
0%
1$
#35
1!
1%
