ehd_project/comp_8.v

module comp8(a,b,l,g,eq);
input [7:0] a;
input [7:0] b;
output l,g,eq;
comp4 f_8(a[3:0], b[3:0],lt0,gt0, equ0);
comp4 s_8(a[7:4], b[7:4],lt1,gt1, equ1);
assign l=(lt0 | lt1) && (~gt1);
assign g=(gt0 | gt1) && (~lt1);
assign eq=equ0 && equ1;
endmodule

ehd_project/final.v
//`include "comp_8.v"
module insertion(clk,reset,sorted,in);//,in2,in3,in4,in5,in6,in7,in8);
	input clk;
	input reset;
	input[31:0] in;//,in2,in3,in4,in5,in6,in7,in8;
	output reg[31:0] sorted;
	integer count=8;//considering count to be a 32 bit number
	reg done=0;
	reg[31:0] in_index=0;
	reg[31:0] out_index=0;
	reg[31:0] sorting[100:0];
	//reg[4:0] i;//
	//reg[4:0] j;//iterating through 32 numbers 
	integer i;
	integer j;
	reg[31:0] key;
	reg valid_in=0;
	reg[1:0] state=0;
	//comp8 c(sorting[j],key,l,g,eq);

	always @(negedge reset) begin
		if (reset==0) begin
			done=0;
			in_index=0;
			out_index=0;
		end
	end
	always @(posedge clk) begin
		/*if (reset==0) begin
			//state=0;
			done=0;
			in_index=0;
			out_index=0;
		end*/
		if(state==0 ) 
		begin
			i=0;
			j=0;
			//sorting[0]=in1;
			//sorting[1]=in2;
			if(in_index<count)
			begin
				sorting[in_index]=in;
				//$display(sorting[in_index]);
				in_index=in_index+1;
			end
			else begin
				state=1;
			end
			
		end
		else if(state==1)
		begin
			i=i+1;
			key = sorting[i];//assigning a value to a temporary register
			//
			if(i<count)
			begin
				state=2;
				//goes to the inner loop (state =2)where comparisons are made 
				j=i-1;
			end
			else 
			begin
				state=3;
				//sorting has been completed 	
			end
		end
		else if(state==2) 
		begin
			if(sorting[j]>key)
			begin
				sorting[j+1] = sorting[j];
				//swapping
				sorting[j]=key;
				//$display(key);
			end
			if(j==0)
			begin
					//to go to the outer loop when comparisons till the 1st element is done
					state=1;
			end
			else begin
					
					state=2;
					//decreasing the index to compare with the other elements 
					j=j-1;
					
			end
			
		end
		else if(state==3) 
		begin
			if(out_index<count)//writing sorted data into output array
			begin
				sorted=sorting[out_index];
				out_index=out_index+1;
			end
			else begin
				state=0;
				done=1;
			end
		end
	end
endmodule

ehd_project/tb.v
module tb;	
	reg clk=0;
	reg[31:0] in;//,in2,in3,in4,in5,in6,in7,in8;
	wire[31:0] sorted; 
	//reg[31:0] count;
	reg reset=1;
	//insertionsort ins(clk,in,sorted,count,reset);
	//forins ff(clk,reset,in,sorted);//in1,in2,in3,in4,in5,in6,in7,in8);
	insertion ii(clk,reset,sorted,in);//in1,in2,in3,in4,in5,in6,in7,in8);
	//always begin
	//clk=1;
	//#100; clk=~(clk);
	//end
	initial begin
		//count=8;
		in <= 100;//64
		//$display(in);
		#1000
		//$display("o");
		//$display(in);
		#1000
		in <= 94;
		//$display(in);
		#1000
		#1000
		in <= 54;//36
		//$display(in);
		#1000
		#1000
		in <= 32;
		//$display(in);
		#1000
		#1000
		in <= 24;//18
		//$display(in);
		#1000
		#1000
		in <= 19;//
		//$display(in);
		#1000
		#1000
		in <= 14;//E
		//$display(in);
		#1000
		#1000
		in <= 2;//2
		//$display(in);
		#100000;
		#100000
		//$display(sorted);
		// $display(sorted[15:8]);
		// $display(sorted[23:16]);
		// $display(sorted[31:24]);
		// $display(sorted[39:32]);
		// $display(sorted[47:40]);
		// $display(sorted[55:48]);
		// $display(sorted[63:56]);
	 $finish;
	end
	always #1000 clk = ~clk;
	initial begin
		$dumpfile("instb.vcd");
		$dumpvars(0,tb);
	end
endmodule

ehd_project/instb.vcd
$date
	Tue Dec  4 15:50:29 2018
$end
$version
	Icarus Verilog
$end
$timescale
	1s
$end
$scope module tb $end
$var wire 32 ! sorted [31:0] $end
$var reg 1 " clk $end
$var reg 32 # in [31:0] $end
$var reg 1 $ reset $end
$scope module ii $end
$var wire 1 " clk $end
$var wire 32 % in [31:0] $end
$var wire 1 $ reset $end
$var reg 1 & done $end
$var reg 32 ' in_index [31:0] $end
$var reg 32 ( key [31:0] $end
$var reg 32 ) out_index [31:0] $end
$var reg 32 * sorted [31:0] $end
$var reg 2 + state [1:0] $end
$var reg 1 , valid_in $end
$var integer 32 - count [31:0] $end
$var integer 32 . i [31:0] $end
$var integer 32 / j [31:0] $end
$upscope $end
$upscope $end
$enddefinitions $end
#0
$dumpvars
bx /
bx .
b1000 -
0,
b0 +
bx *
b0 )
bx (
b0 '
0&
b1100100 %
1$
b1100100 #
0"
bx !
$end
#1000
b1 '
b0 /
b0 .
1"
#2000
b1011110 #
b1011110 %
0"
#3000
b10 '
1"
#4000
b110110 #
b110110 %
0"
#5000
b11 '
1"
#6000
b100000 #
b100000 %
0"
#7000
b100 '
1"
#8000
b11000 #
b11000 %
0"
#9000
b101 '
1"
#10000
b10011 #
b10011 %
0"
#11000
b110 '
1"
#12000
b1110 #
b1110 %
0"
#13000
b111 '
1"
#14000
b10 #
b10 %
0"
#15000
b1000 '
1"
#16000
0"
#17000
b1 +
1"
#18000
0"
#19000
b10 +
b1011110 (
b1 .
1"
#20000
0"
#21000
b1 +
1"
#22000
0"
#23000
b1 /
b10 +
b110110 (
b10 .
1"
#24000
0"
#25000
b0 /
1"
#26000
0"
#27000
b1 +
1"
#28000
0"
#29000
b10 /
b10 +
b100000 (
b11 .
1"
#30000
0"
#31000
b1 /
1"
#32000
0"
#33000
b0 /
1"
#34000
0"
#35000
b1 +
1"
#36000
0"
#37000
b11 /
b10 +
b11000 (
b100 .
1"
#38000
0"
#39000
b10 /
1"
#40000
0"
#41000
b1 /
1"
#42000
0"
#43000
b0 /
1"
#44000
0"
#45000
b1 +
1"
#46000
0"
#47000
b100 /
b10 +
b10011 (
b101 .
1"
#48000
0"
#49000
b11 /
1"
#50000
0"
#51000
b10 /
1"
#52000
0"
#53000
b1 /
1"
#54000
0"
#55000
b0 /
1"
#56000
0"
#57000
b1 +
1"
#58000
0"
#59000
b101 /
b10 +
b1110 (
b110 .
1"
#60000
0"
#61000
b100 /
1"
#62000
0"
#63000
b11 /
1"
#64000
0"
#65000
b10 /
1"
#66000
0"
#67000
b1 /
1"
#68000
0"
#69000
b0 /
1"
#70000
0"
#71000
b1 +
1"
#72000
0"
#73000
b110 /
b10 +
b10 (
b111 .
1"
#74000
0"
#75000
b101 /
1"
#76000
0"
#77000
b100 /
1"
#78000
0"
#79000
b11 /
1"
#80000
0"
#81000
b10 /
1"
#82000
0"
#83000
b1 /
1"
#84000
0"
#85000
b0 /
1"
#86000
0"
#87000
b1 +
1"
#88000
0"
#89000
b11 +
bx (
b1000 .
1"
#90000
0"
#91000
b1 )
b10 !
b10 *
1"
#92000
0"
#93000
b10 )
b1110 !
b1110 *
1"
#94000
0"
#95000
b11 )
b10011 !
b10011 *
1"
#96000
0"
#97000
b100 )
b11000 !
b11000 *
1"
#98000
0"
#99000
b101 )
b100000 !
b100000 *
1"
#100000
0"
#101000
b110 )
b110110 !
b110110 *
1"
#102000
0"
#103000
b111 )
b1011110 !
b1011110 *
1"
#104000
0"
#105000
b1000 )
b1100100 !
b1100100 *
1"
#106000
0"
#107000
1&
b0 +
1"
#108000
0"
#109000
b1 +
b0 .
1"
#110000
0"
#111000
b10 +
b1110 (
b1 .
1"
#112000
0"
#113000
b1 +
1"
#114000
0"
#115000
b1 /
b10 +
b10011 (
b10 .
1"
#116000
0"
#117000
b0 /
1"
#118000
0"
#119000
b1 +
1"
#120000
0"
#121000
b10 /
b10 +
b11000 (
b11 .
1"
#122000
0"
#123000
b1 /
1"
#124000
0"
#125000
b0 /
1"
#126000
0"
#127000
b1 +
1"
#128000
0"
#129000
b11 /
b10 +
b100000 (
b100 .
1"
#130000
0"
#131000
b10 /
1"
#132000
0"
#133000
b1 /
1"
#134000
0"
#135000
b0 /
1"
#136000
0"
#137000
b1 +
1"
#138000
0"
#139000
b100 /
b10 +
b110110 (
b101 .
1"
#140000
0"
#141000
b11 /
1"
#142000
0"
#143000
b10 /
1"
#144000
0"
#145000
b1 /
1"
#146000
0"
#147000
b0 /
1"
#148000
0"
#149000
b1 +
1"
#150000
0"
#151000
b101 /
b10 +
b1011110 (
b110 .
1"
#152000
0"
#153000
b100 /
1"
#154000
0"
#155000
b11 /
1"
#156000
0"
#157000
b10 /
1"
#158000
0"
#159000
b1 /
1"
#160000
0"
#161000
b0 /
1"
#162000
0"
#163000
b1 +
1"
#164000
0"
#165000
b110 /
b10 +
b1100100 (
b111 .
1"
#166000
0"
#167000
b101 /
1"
#168000
0"
#169000
b100 /
1"
#170000
0"
#171000
b11 /
1"
#172000
0"
#173000
b10 /
1"
#174000
0"
#175000
b1 /
1"
#176000
0"
#177000
b0 /
1"
#178000
0"
#179000
b1 +
1"
#180000
0"
#181000
b11 +
bx (
b1000 .
1"
#182000
0"
#183000
b0 +
1"
#184000
0"
#185000
b1 +
b0 .
1"
#186000
0"
#187000
b10 +
b1110 (
b1 .
1"
#188000
0"
#189000
b1 +
1"
#190000
0"
#191000
b1 /
b10 +
b10011 (
b10 .
1"
#192000
0"
#193000
b0 /
1"
#194000
0"
#195000
b1 +
1"
#196000
0"
#197000
b10 /
b10 +
b11000 (
b11 .
1"
#198000
0"
#199000
b1 /
1"
#200000
0"
#201000
b0 /
1"
#202000
0"
#203000
b1 +
1"
#204000
0"
#205000
b11 /
b10 +
b100000 (
b100 .
1"
#206000
0"
#207000
b10 /
1"
#208000
0"
#209000
b1 /
1"
#210000
0"
#211000
b0 /
1"
#212000
0"
#213000
b1 +
1"
