lab2/state.v
module state(in,out,rst);
	input in,rst;
	output out;
	reg[2:0] state;
	assign out = (state[2])&&(!state[1])&&(!state[0]);
	always @(posedge in or rst) begin
		if (!rst) begin
			state <= 3'b0;
		end
		else if (state != 3'b100) begin
			state <= state + 1'b1;
		end
		else begin
			state <= 3'b001;
		end
	end
endmodule

lab2/tstbstate.v
`include "state.v"
module test;
	reg in;
	reg rst;
	wire out;
	//rst = 0;
	state s(in,out,rst);
	initial begin
	  rst=0; 
	  repeat(1)
	  #2 rst=~(rst);
	end   
	initial begin
		in <= 1'b0;
	#1
		in <= 1'b1;
	#2
		in <= 1'b0;
	#1
		in <= 1'b1;
	#3
		in <= 1'b0;
	#1
		in <= 1'b1;
	#5
		in <= 1'b0;
	#2
		in <= 1'b1;
	#1
		in <= 1'b0;
	#1
		in <= 1'b1;
	#1
		in <= 1'b0;
	#1
		in <= 1'b1;
	#1
		in <= 1'b0;
	#1
		in <= 1'b1;
	#1
		in <= 1'b0;
	#1
		in <= 1'b1;
	#1
		in <= 1'b0;
	#1
		in <= 1'b1;
	#1
		in <= 1'b0;
	#1
		in <= 1'b1;																	
	end
	initial begin
		$dumpfile("statedump.vcd");
		$dumpvars(0,test);
	end
endmodule

lab2/statedump.vcd
$date
	Sat Aug 11 18:45:54 2018
$end
$version
	Icarus Verilog
$end
$timescale
	1s
$end
$scope module test $end
$var wire 1 ! out $end
$var reg 1 " in $end
$var reg 1 # rst $end
$scope module s $end
$var wire 1 " in $end
$var wire 1 ! out $end
$var wire 1 # rst $end
$var reg 3 $ state [2:0] $end
$upscope $end
$upscope $end
$enddefinitions $end
#0
$dumpvars
b0 $
0#
0"
0!
$end
#1
1"
#2
b1 $
1#
#3
0"
#4
b10 $
1"
#7
0"
#8
b11 $
1"
#13
0"
#15
1!
b100 $
1"
#16
0"
#17
0!
b1 $
1"
#18
0"
#19
b10 $
1"
#20
0"
#21
b11 $
1"
#22
0"
#23
1!
b100 $
1"
#24
0"
#25
0!
b1 $
1"
#26
0"
#27
b10 $
1"
